clustercast/__init__.py
clustercast/clustercast.py
clustercast/datasets/__init__.py
clustercast/datasets/data/airline_passengers.csv
clustercast/datasets/data/store_sales.csv
clustercast-0.1.1.dist-info/LICENSE
clustercast-0.1.1.dist-info/METADATA
clustercast-0.1.1.dist-info/WHEEL
clustercast-0.1.1.dist-info/RECORD
