Metadata-Version: 2.3
Name: clustercast
Version: 0.1.1
Summary: A model-agnostic global forecasting framework for grouped time series analysis.
License: MIT
Author: Alex Dundore
Author-email: acdundore.5@gmail.com
Requires-Python: >=3.12,<4.0
Classifier: License :: OSI Approved :: MIT License
Classifier: Programming Language :: Python :: 3
Classifier: Programming Language :: Python :: 3.12
Classifier: Programming Language :: Python :: 3.13
Requires-Dist: lightgbm (>=4.5.0,<5.0.0)
Requires-Dist: numpy (>=1.26.0,<2.0.0)
Requires-Dist: pandas (>=2.2.3,<3.0.0)
Requires-Dist: statsmodels (>=0.14.4,<0.15.0)
Project-URL: Documentation, https://acdundore.github.io/clustercast/
Project-URL: Homepage, https://pypi.org/project/clustercast
Project-URL: Repository, https://github.com/acdundore/clustercast
